[{"name":"検査","value":9},{"name":"者","value":8},{"name":"人","value":6},{"name":"感染","value":6},{"name":"状況","value":6},{"name":"症状","value":6},{"name":"ゲノム","value":5},{"name":"今","value":5},{"name":"ウイルス","value":4},{"name":"モニタリング","value":4},{"name":"話","value":4},{"name":"判断","value":4},{"name":"ステージ","value":4},{"name":"重要","value":4},{"name":"指標","value":4},{"name":"書く","value":3},{"name":"値","value":3},{"name":"見る","value":3},{"name":"量","value":3},{"name":"株","value":3},{"name":"的","value":3},{"name":"出す","value":3},{"name":"N","value":3},{"name":"我々","value":3},{"name":"状","value":3},{"name":"考える","value":3},{"name":"Ct","value":3},{"name":"陽性","value":3},{"name":"今回","value":3},{"name":"有症","value":3},{"name":"501","value":2},{"name":"研","value":2},{"name":"Y","value":2},{"name":"初期","value":2},{"name":"資料","value":2},{"name":"従来","value":2},{"name":"低い","value":2},{"name":"多い","value":2},{"name":"高い","value":2},{"name":"リアルタイム","value":2},{"name":"必要","value":2},{"name":"施策","value":2},{"name":"施設","value":2},{"name":"引っかける","value":2},{"name":"風邪","value":2},{"name":"受診","value":2},{"name":"管理","value":2},{"name":"あぶる","value":2},{"name":"非常","value":2},{"name":"解析","value":2},{"name":"示す","value":2},{"name":"専門","value":2},{"name":"いける","value":2},{"name":"ここ","value":2},{"name":"難しい","value":2},{"name":"ページ","value":2},{"name":"４","value":2},{"name":"家","value":2},{"name":"拡大","value":2},{"name":"スピード","value":1},{"name":"言う","value":1},{"name":"議論","value":1},{"name":"捉える","value":1},{"name":"熱","value":1},{"name":"最近","value":1},{"name":"大事","value":1},{"name":"検出","value":1},{"name":"導く","value":1},{"name":"確率","value":1},{"name":"事前","value":1},{"name":"感","value":1},{"name":"効率","value":1},{"name":"支援","value":1},{"name":"執行","value":1},{"name":"業務","value":1},{"name":"度","value":1},{"name":"物資","value":1},{"name":"人材","value":1},{"name":"体制","value":1},{"name":"衛生","value":1},{"name":"公衆","value":1},{"name":"られる","value":1},{"name":"切れる","value":1},{"name":"街角","value":1},{"name":"大阪","value":1},{"name":"37","value":1},{"name":"軽い","value":1},{"name":"５","value":1},{"name":"分","value":1},{"name":"そこ","value":1},{"name":"側面","value":1},{"name":"見える","value":1},{"name":"特性","value":1},{"name":"持つ","value":1},{"name":"一定","value":1},{"name":"化","value":1},{"name":"多様","value":1},{"name":"込む","value":1},{"name":"入れる","value":1},{"name":"どこ","value":1},{"name":"促進","value":1},{"name":"診療","value":1},{"name":"持ち込む","value":1},{"name":"特段","value":1},{"name":"イベントベースドサーベイランス","value":1},{"name":"意見","value":1},{"name":"職場","value":1},{"name":"含める","value":1},{"name":"CHAT","value":1},{"name":"-","value":1},{"name":"迅速","value":1},{"name":"結局","value":1},{"name":"等","value":1},{"name":"以上","value":1},{"name":"進む","value":1},{"name":"高齢","value":1},{"name":"入る","value":1},{"name":"年末","value":1},{"name":"E","value":1},{"name":"速度","value":1},{"name":"性","value":1},{"name":"可能","value":1},{"name":"今週","value":1},{"name":"つながる","value":1},{"name":"基準","value":1},{"name":"退院","value":1},{"name":"出る","value":1},{"name":"結果","value":1},{"name":"目","value":1},{"name":"日","value":1},{"name":"７","value":1},{"name":"減る","value":1},{"name":"先週","value":1},{"name":"比","value":1},{"name":"PCR","value":1},{"name":"率","value":1},{"name":"今後","value":1},{"name":"予測","value":1},{"name":"疫学","value":1},{"name":"分析","value":1},{"name":"会","value":1},{"name":"分科","value":1},{"name":"総合","value":1},{"name":"484","value":1},{"name":"K","value":1},{"name":"案","value":1},{"name":"６","value":1},{"name":"年始","value":1},{"name":"考え方","value":1},{"name":"年度替わり","value":1},{"name":"重点的","value":1},{"name":"世の中","value":1},{"name":"事業","value":1},{"name":"対","value":1},{"name":"様々","value":1},{"name":"講ずる","value":1},{"name":"関わる","value":1},{"name":"以降","value":1},{"name":"配る","value":1},{"name":"地域","value":1},{"name":"機械","value":1},{"name":"いただける","value":1},{"name":"衛","value":1},{"name":"地","value":1},{"name":"出せる","value":1},{"name":"流","value":1},{"name":"データ","value":1},{"name":"県","value":1},{"name":"鳥取","value":1},{"name":"公表","value":1},{"name":"アドバイザリーボード","value":1},{"name":"書き込む","value":1}]